{
    "Marketing": {
        "Brand Management": {
            "soft skills": [
                "collaboration",
                "communication",
                "conflict resolution",
                "creativity",
                "critical thinking",
                "decision making",
                "detail",
                "development",
                "education",
                "flexibility",
                "implementation",
                "innovation",
                "interaction",
                "interpretation",
                "leadership",
                "listening",
                "mentoring",
                "multi-tasking",
                "negotiating",
                "networking",
                "organization",
                "organizational",
                "planning",
                "presentation",
                "problem-solving",
                "project management",
                "public speaking",
                "relationship building",
                "research",
                "standards",
                "strategic thinking",
                "strategizing",
                "teamwork",
                "time-management"
            ],
            "technical skills": [
                "PR",
                "SEO",
                "ability",
                "advertising",
                "advertising fundamentals",
                "analysis",
                "analytical skills",
                "brand development",
                "brand management",
                "brand strategy",
                "budgeting",
                "business analytics",
                "campaign execution",
                "campaign planning",
                "certification",
                "client engagement",
                "communication strategies",
                "consumer insights",
                "content creation",
                "content development",
                "content merchandising",
                "creative development",
                "crisis management",
                "customer service",
                "data analysis",
                "data analytics",
                "development",
                "digital campaigns",
                "execution",
                "experience",
                "financial analysis",
                "financial management",
                "floor operations",
                "food",
                "growth marketing",
                "implementation",
                "knowledge",
                "management",
                "market analysis",
                "market research",
                "marketing",
                "media",
                "media planning",
                "media relations",
                "mentoring",
                "offline brand experiences",
                "phone etiquette",
                "product development",
                "product innovation",
                "product management",
                "product positioning",
                "proficiency",
                "project management",
                "public relations",
                "relationship management",
                "reporting",
                "research",
                "research skills",
                "reservation systems",
                "sales",
                "sales support",
                "social media",
                "social media strategy",
                "strategic planning",
                "strategy",
                "strategy management",
                "strategy planning",
                "supply chain",
                "tactical activities",
                "training",
                "understanding",
                "wine",
                "writing"
            ]
        },
        "Marketing Communications": {
            "soft skills": [
                "active listening",
                "adaptability",
                "agility",
                "analysis",
                "analytical",
                "analytical mindset",
                "analytical thinking",
                "analytics",
                "analyzing",
                "attention",
                "attention to detail",
                "authenticity",
                "collaboration",
                "communication",
                "community",
                "community management",
                "consideration",
                "constructing",
                "coordinating",
                "creative",
                "creative problem-solving",
                "creativity",
                "critical thinking",
                "data gathering & analysis",
                "detail orientation",
                "detail-oriented",
                "energetic",
                "energy",
                "engagement",
                "evaluating",
                "excellence",
                "feedback",
                "flexibility",
                "growth",
                "influence",
                "interpersonal",
                "kindness",
                "leadership",
                "learning",
                "managing",
                "mentoring",
                "moderation",
                "monitoring",
                "motivation",
                "networking",
                "openness",
                "organization",
                "ownership",
                "planning & organizing",
                "positive attitude",
                "presentation",
                "presentation skills",
                "prioritization",
                "proactive",
                "proactive monitoring",
                "proactivity",
                "problem solving",
                "problem-solving",
                "proofreading",
                "quality focused",
                "realizing",
                "reinvention",
                "relationship",
                "relationship building",
                "relationship-building",
                "reporting",
                "research",
                "respect",
                "results-oriented",
                "scheduling",
                "self starter",
                "self-motivated",
                "strategic mindset",
                "strategic planning",
                "strategic thinking",
                "strategy",
                "support",
                "teamwork",
                "time management",
                "time-management",
                "training and development",
                "understanding",
                "upbeat attitude"
            ],
            "technical skills": [
                "A/B testing",
                "Ahrefs",
                "CMS management",
                "CRM",
                "CSS",
                "Excel",
                "Freedonomics",
                "Google Ads",
                "Google Analytics",
                "Google Docs",
                "Google Merchant Center",
                "Google Search Console",
                "Google Workspace",
                "HTML",
                "JavaScript",
                "KPI analysis",
                "KPI creation",
                "Microsoft Office",
                "PR",
                "PR management",
                "PR strategy development",
                "PowerPoint",
                "Python",
                "QA",
                "SEM",
                "SEM Rush",
                "SEO",
                "SEO knowledge",
                "SEO optimization",
                "SEO writing",
                "SQL",
                "ScreamingFrog",
                "Word",
                "advertising",
                "ahrefs",
                "analysis",
                "analytical",
                "analytics",
                "assessing",
                "attribution modeling",
                "audio production",
                "audio visual",
                "automation",
                "bing ads manager",
                "blog",
                "brand awareness",
                "brand growth",
                "brand management",
                "brand strategy",
                "branding",
                "budget management",
                "budgeting",
                "business communications",
                "campaign",
                "campaign management",
                "campaign performance measurement",
                "campaign strategy",
                "campaigns",
                "carrying",
                "client",
                "collaborating",
                "collaboration",
                "communication",
                "communication capabilities",
                "communication strategy",
                "communications",
                "communications research",
                "communicator",
                "compiling",
                "computer keyboarding skills",
                "content",
                "content calendar",
                "content calendar management",
                "content creation",
                "content development",
                "content distribution",
                "content ideation",
                "content management",
                "content management system",
                "content management systems",
                "content marketing",
                "content optimization",
                "content planning",
                "content strategy",
                "content updates",
                "content writing",
                "conversion rate optimization",
                "coordinating",
                "copywriting",
                "creative",
                "creative suite",
                "crisis management",
                "crm",
                "crms",
                "css",
                "customer engagement",
                "customer experience",
                "customer service",
                "data",
                "data analysis",
                "data analytics",
                "data manipulation",
                "data processing",
                "data-driven",
                "data-driven marketing",
                "developing",
                "digital",
                "digital PR",
                "digital advertising",
                "digital analytics",
                "digital design",
                "digital display campaigns",
                "digital marketing",
                "digital marketing strategies",
                "digital media",
                "digital media campaigns",
                "display analytics",
                "drafting",
                "ecommerce",
                "edit",
                "editing",
                "editorial strategy",
                "email",
                "email campaigns management",
                "email marketing",
                "engagement",
                "event coordination",
                "event management",
                "event planning",
                "event programs",
                "event programs development",
                "event strategy development",
                "executing",
                "execution",
                "facebook ads",
                "facebook business manager",
                "feasibility study",
                "following",
                "formatting",
                "fostering",
                "freedonomics",
                "generative AI",
                "google ads",
                "google ads manager",
                "google analytics",
                "google data studio",
                "google my business",
                "google tag manager",
                "graphic design",
                "healthcare markets",
                "html",
                "image editing",
                "improving",
                "inbound strategy",
                "innovating",
                "instagram ads",
                "interactive research tools",
                "interviewing",
                "journalism",
                "juggling",
                "keyword research",
                "landing pages",
                "language localization",
                "lead generation",
                "linkedin",
                "linkedin ads",
                "linkedin campaign manager",
                "local seo",
                "management",
                "managing",
                "market analysis",
                "market research",
                "marketing",
                "marketing automation",
                "marketing calendar planning",
                "marketing campaign development",
                "marketing experience",
                "media",
                "media analysis",
                "media credentials",
                "media management",
                "media mix modeling",
                "media operations",
                "media planning",
                "media relations",
                "media relations expertise",
                "media room management",
                "media strategy",
                "merchant center",
                "messaging map",
                "meta business suite",
                "metrics",
                "monitoring",
                "motion graphics",
                "multimedia content production",
                "multimedia solutions",
                "negotiation skills",
                "offline brand experiences",
                "optimization",
                "optimize",
                "optimizing",
                "organizing",
                "overseeing",
                "paid search",
                "paid social",
                "partnering",
                "pay-per-click advertising",
                "phone etiquette",
                "planning",
                "planning tools",
                "post-game press conferences",
                "ppc campaigns",
                "problem-solving",
                "proficiency",
                "programmatic",
                "programmatic advertising",
                "project coordination",
                "project management",
                "promoting",
                "promotional items purchasing",
                "proofread",
                "proofreading",
                "prospect-facing communications",
                "public relations",
                "public relations expertise",
                "report building",
                "reporting",
                "research",
                "reservation systems",
                "revise",
                "sales",
                "scheduling",
                "screamingfrog",
                "screening",
                "search",
                "search console",
                "search engine marketing",
                "search engine optimization",
                "sem rush",
                "seo",
                "seo/sem tools",
                "social media",
                "social media analytics",
                "social media knowledge",
                "social media management",
                "social media marketing",
                "statistical records maintenance",
                "strategy",
                "supporting",
                "tag manager",
                "teaching",
                "time management",
                "twitter ads",
                "typing",
                "video editing",
                "video production",
                "video strategy",
                "web",
                "web analytics",
                "web design",
                "web management",
                "webinar production",
                "website CMS",
                "website maintenance",
                "wordpress",
                "writing",
                "youtube ads"
            ]
        },
        "Digital Marketing": {
            "soft skills": [
                "accountability",
                "achieving objectives",
                "adaptability",
                "analytical",
                "analytical skills",
                "analytical thinking",
                "analyzing",
                "anticipate needs",
                "attention to detail",
                "autonomy",
                "build initiatives",
                "building relationships",
                "business literacy",
                "campaigns",
                "client management",
                "coaching",
                "collaborate",
                "collaboration",
                "commitment",
                "communicate",
                "communicates value",
                "communication",
                "communication skills",
                "community management",
                "confident",
                "conflict resolution",
                "content creation",
                "craft messaging",
                "creating environment",
                "creating materials",
                "creating messages",
                "creative",
                "creative problem-solving",
                "creative thinking",
                "creativity",
                "critical thinking",
                "curiosity",
                "customer satisfaction",
                "cycle-to-work",
                "decision-making",
                "deliver messaging",
                "detail-oriented",
                "develop brand",
                "develop collateral",
                "develop strategies",
                "developing plans",
                "differentiate products",
                "diligence",
                "discretion",
                "diversity",
                "drive adoption",
                "drive strategy",
                "driving revenue",
                "editing",
                "educate customers",
                "education",
                "effective communication",
                "engagement",
                "evaluate results",
                "facilitation",
                "flexibility",
                "frequent team socials",
                "friendly",
                "gather feedback",
                "generate objectives",
                "hands-on approach",
                "humility",
                "ideation",
                "identify opportunities",
                "increase usage",
                "independent",
                "initiative",
                "innovation",
                "innovative",
                "interact",
                "interaction",
                "interpersonal",
                "interpersonal skills",
                "knowledge-sharing",
                "leadership",
                "leverage insights",
                "logical thinking",
                "loyal",
                "manage campaigns",
                "managing",
                "managing strategies",
                "maximize value",
                "mentoring",
                "multitasking",
                "mutual respect",
                "negotiation",
                "optimization",
                "optimize performance",
                "optimizing",
                "organization",
                "organizational skills",
                "organizing",
                "ownership",
                "patience",
                "persistence",
                "planning",
                "proactive",
                "proactiveness",
                "problem solving",
                "problem-solving",
                "process improvement",
                "professional attitude",
                "project management",
                "proofreading",
                "quick learner",
                "recommendations",
                "refine messaging",
                "refinement",
                "relationship management",
                "reporting",
                "research",
                "research skills",
                "resident relations",
                "resourceful",
                "results-oriented",
                "self-manage",
                "self-motivated",
                "service-minded",
                "social events",
                "staff performance",
                "stay connected",
                "strategic",
                "strategic thinking",
                "strategy development",
                "success stories",
                "supportiveness",
                "tailored content",
                "team-oriented",
                "teamwork",
                "time management",
                "work closely",
                "work effectively",
                "working closely",
                "writing",
                "writing skills"
            ],
            "technical skills": [
                "6Sense",
                "A/B Testing",
                "A/B testing",
                "ARIMA",
                "ASO",
                "Adobe After Effects",
                "Adobe Analytics",
                "Adobe Creative Suite",
                "Adobe Illustrator",
                "Adobe Photoshop",
                "Ahrefs",
                "Baidu",
                "Bing Ads Manager",
                "CAN-SPAM Laws",
                "CMS",
                "CRM",
                "CRM Software",
                "CRM management",
                "CSS",
                "CSS handling",
                "Canva",
                "Cluster Analysis",
                "Cohort Analysis",
                "Constant Contact",
                "Content Marketing",
                "Customer Segmentation",
                "Data Analysis",
                "Deliverability",
                "Digital Marketing",
                "Display Advertising",
                "Email Marketing",
                "Excel",
                "Facebook Ads",
                "Facebook Business Manager",
                "G Suite",
                "Google Ads",
                "Google Ads Manager",
                "Google Analytics",
                "Google Analytics 4",
                "Google Business Profile",
                "Google Docs",
                "Google Merchant Center",
                "Google My Business",
                "Google Search Console",
                "Google Sheets",
                "Google Tag Manager",
                "Growth Marketing",
                "HTML",
                "HTML handling",
                "HTML skills",
                "HTML/CSS",
                "Hootsuite",
                "Hubspot",
                "Hubspot CRM",
                "Hypothesis Testing",
                "JavaScript",
                "Javascript",
                "KPI analysis",
                "Keyword Research",
                "Lifecycle Marketing",
                "Line",
                "Link Building",
                "LinkedIn Ads",
                "LinkedIn Advertising",
                "LinkedIn Campaign Manager",
                "List Management",
                "MI requirements",
                "MQL/SQL",
                "MailChimp",
                "Mailchimp",
                "Market Automation Platforms",
                "Marketing Automation",
                "Meta Ads",
                "Microsoft 365 solutions",
                "Microsoft Ads",
                "Microsoft Excel",
                "Microsoft Office",
                "Moz",
                "Online Advertising",
                "PHP",
                "PO creation",
                "PPC",
                "PPC campaigns",
                "PPC strategies",
                "PR coordination",
                "Power BI",
                "PowerBI",
                "Python",
                "QA",
                "R",
                "Regression",
                "SAS",
                "SEM",
                "SEM Rush",
                "SEM and SEO",
                "SEMrush",
                "SEO",
                "SEO best practices",
                "SEO improvement",
                "SEO knowledge",
                "SEO optimization",
                "SEO strategies",
                "SEO techniques",
                "SEO tools",
                "SEO writing",
                "SEO/SEM",
                "SEO/SEM tools",
                "SQL",
                "SQL queries",
                "Salesforce",
                "ScreamingFrog",
                "Site Analysis",
                "Social Media Marketing",
                "Tableau",
                "TikTok",
                "TikTok Ads",
                "UX design",
                "UX principles",
                "WeChat",
                "Web Analytics",
                "Webflow",
                "WordPress",
                "WordPress management",
                "WordPress plugins",
                "WordPress themes",
                "account management",
                "accounting processes",
                "affiliate marketing",
                "analytical",
                "analytical skills",
                "analytical tools",
                "analytics",
                "analytics and reporting",
                "analyzing",
                "analyzing metrics",
                "automation",
                "back-end development",
                "blockchain",
                "blog posts",
                "blogging",
                "brand management",
                "budget assessments",
                "budget preparation",
                "business analysis",
                "campaign effectiveness",
                "campaign management",
                "case studies",
                "client offboarding",
                "client onboarding",
                "client relationship management",
                "coding (HTML/CSS)",
                "community appearance verification",
                "community management",
                "competitive analysis",
                "competitive property shopping",
                "compliance",
                "compliance management",
                "confidence intervals",
                "content calendar execution",
                "content collaboration",
                "content configuration",
                "content creation",
                "content development",
                "content management",
                "content management systems",
                "content marketing",
                "content optimization",
                "content planning",
                "content production",
                "content recommendations",
                "content research",
                "content strategy",
                "content strategy development",
                "content writing",
                "contract negotiation",
                "conversion",
                "conversion optimization",
                "copywriting",
                "creative problem solving",
                "crm",
                "crypto",
                "customer journeys",
                "customer usage",
                "dashboards",
                "data analysis",
                "data analytics",
                "data collection",
                "data insights analysis",
                "data integrity management",
                "data management",
                "data platform",
                "data retrieval",
                "data strategy",
                "data tools",
                "data uploading",
                "data visualization",
                "data visualization tools",
                "data-driven marketing",
                "design production",
                "digital advertising",
                "digital analytics",
                "digital asset production",
                "digital marketing",
                "digital/social media marketing",
                "editing",
                "email campaign execution",
                "email campaigns",
                "email coordination",
                "email forms setup",
                "email landing pages",
                "email marketing",
                "email templates",
                "email testing",
                "end-to-end campaigns",
                "engagement marketing",
                "evictions",
                "excel proficiency",
                "executive summaries",
                "financial reporting",
                "financial reports",
                "forecasting",
                "forms setup",
                "front-end development",
                "general administration",
                "generative AI",
                "go-to-market strategies",
                "google analytics",
                "google marketing",
                "graphic design",
                "graphic designing",
                "growth experiments",
                "health tech",
                "healthcare sector",
                "hiring",
                "html/css",
                "image editing",
                "image editing tools",
                "image optimization",
                "inbound leads",
                "industry trends",
                "invoice processing",
                "key performance indicators",
                "keyword research",
                "landing page optimization",
                "landing page optimizations",
                "landing pages",
                "lead generation",
                "lease execution",
                "lease renewals",
                "leasing",
                "leasing matrix",
                "leasing reports",
                "legal notices",
                "link building",
                "maintenance coordination",
                "market research",
                "market surveys",
                "marketing",
                "marketing automation",
                "marketing calendar",
                "marketing campaigns",
                "marketing cloud",
                "marketing collateral",
                "marketing operations",
                "marketing plans",
                "marketing tools",
                "measurement",
                "media buying",
                "media management",
                "metric-driven approach",
                "mobile responsive coding",
                "move in/out coordination",
                "move-ins",
                "move-outs",
                "multi-touch attribution",
                "off-page SEO",
                "office expenses",
                "offline brand experiences",
                "on-page SEO",
                "on-page optimization",
                "online advertising",
                "outbound marketing",
                "page load optimization",
                "paid advertising",
                "pardot",
                "partnering",
                "performance management",
                "performance marketing",
                "performance metrics",
                "personalization",
                "physical inspections",
                "pixel tracking",
                "platforms",
                "product adoption",
                "product materials",
                "product messaging",
                "product positioning",
                "programming",
                "project leadership",
                "project management",
                "property leasing",
                "property management",
                "property operations",
                "prospect-facing communications",
                "public relations",
                "referral program",
                "regression models",
                "reporting",
                "reporting methodologies",
                "reputation management",
                "research",
                "resident delinquencies",
                "resident relations",
                "resident retention",
                "revenue enablement",
                "safety verification",
                "sales",
                "sales enablement",
                "salesforce",
                "scheduling",
                "search engine algorithms",
                "segmentation",
                "seo",
                "site architecture",
                "site-level leadership",
                "smart contract",
                "social content creation",
                "social media",
                "social media advertising",
                "social media analytics",
                "social media management",
                "social media marketing",
                "social media publishing",
                "social media strategies",
                "social media strategy",
                "statistical tools",
                "strategic planning",
                "strategy development",
                "table-based layouts",
                "tech stack",
                "technical SEO",
                "technical audits",
                "tools",
                "track effectiveness",
                "tracking",
                "trading",
                "training",
                "unit conditions verification",
                "upsell opportunities",
                "user experience enhancements",
                "utilities",
                "vendor payables processing",
                "video editing",
                "video production",
                "web analytics",
                "web design",
                "web design languages",
                "web development",
                "web management",
                "web performance",
                "web personalization",
                "webinars",
                "website analysis",
                "website analytics",
                "website audit",
                "website development",
                "website performance analysis",
                "website troubleshooting",
                "website updates",
                "whitepapers",
                "writing"
            ]
        },
        "Product Marketing": {
            "soft skills": [
                "action biased",
                "adaptability",
                "analytical",
                "analytical skills",
                "c-suite navigator",
                "collaboration",
                "communication",
                "consultative",
                "creative skills",
                "creativity",
                "critical thinking",
                "curiosity",
                "customer storyteller",
                "decision making",
                "flexibility",
                "innovation",
                "interpersonal",
                "leadership",
                "organization",
                "ownership",
                "people leader",
                "presentation",
                "pride",
                "prioritization",
                "pro-active attitude",
                "problem-solving",
                "project management",
                "reporting",
                "self-starter",
                "storytelling",
                "teamwork",
                "time-management"
            ],
            "technical skills": [
                "A/B testing",
                "ABM - Account-Based Marketing",
                "AI",
                "Adobe Creative Suite",
                "A|B testing",
                "B2B tech solutions",
                "CRM",
                "CRM management",
                "CRM marketing",
                "CRM tools",
                "CSS",
                "D2C PPC campaigns",
                "GTM strategy",
                "Google Analytics",
                "HTML",
                "JavaScript",
                "KPI tracking",
                "MS Office proficiency",
                "PPC campaigns",
                "ROI analysis",
                "ROI tracking",
                "SEM",
                "SEM campaigns",
                "SEO",
                "SEO best practices",
                "SEO content writing",
                "SEO focus",
                "SEO strategies",
                "SWOT analysis",
                "SaaS",
                "UX principles",
                "account-based marketing",
                "affiliate marketing",
                "analysis",
                "analytical",
                "analytical skills",
                "analytics",
                "automation",
                "automation tools",
                "brand awareness",
                "budget management",
                "budgeting",
                "budgets",
                "campaign management",
                "campaign optimization",
                "campaign performance analysis",
                "case study creation",
                "client relations",
                "collateral development",
                "competitive analysis",
                "competitive intelligence",
                "content creation",
                "content development",
                "content marketing",
                "content marketing strategy",
                "content optimization",
                "content plan",
                "content strategy",
                "conversion tracking",
                "copywriting",
                "cross-functional alignment",
                "cross-functional collaboration",
                "customer engagement",
                "customer feedback",
                "customer insight",
                "customer insights",
                "customer journey",
                "customer relationship management",
                "customer success",
                "data accuracy",
                "data analysis",
                "data analytics",
                "data visualization",
                "data-driven",
                "data-driven marketing",
                "demand generation",
                "digital advertising",
                "digital asset production",
                "digital display campaigns",
                "digital marketing",
                "email marketing",
                "event management",
                "feature prioritization",
                "forecasting",
                "go-to-market planning",
                "go-to-market strategy",
                "graphic design",
                "image optimization",
                "inbound content strategy",
                "integration",
                "keyword research",
                "landing page optimization",
                "lead generation",
                "link building",
                "local SEO strategies",
                "market analysis",
                "market expertise",
                "market intelligence",
                "market opportunity assessment",
                "market positioning",
                "market research",
                "market research analysis",
                "marketing",
                "marketing analytics",
                "marketing automation",
                "marketing collateral",
                "marketing operations",
                "marketing technology",
                "media buying models",
                "message crafting",
                "messaging and content alignment",
                "messaging and positioning",
                "metrics",
                "metrics and reporting",
                "metrics execution",
                "multi-channel marketing",
                "omnichannel marketing",
                "online customer acquisition",
                "packaging",
                "pay-per-click campaigns",
                "performance marketing",
                "pipeline management",
                "presentation skills",
                "pricing",
                "pricing strategy",
                "product adoption",
                "product development",
                "product launch",
                "product launch strategy",
                "product lifecycle management",
                "product management",
                "product marketing",
                "product messaging",
                "product positioning",
                "project leadership",
                "project management",
                "quantitative methods",
                "reporting",
                "research",
                "sales",
                "sales collateral",
                "sales enablement",
                "sales management",
                "social media ad campaigns",
                "social media management",
                "social media marketing",
                "social media strategy",
                "software development",
                "solution design",
                "solutioning",
                "statistical analysis",
                "strategic planning",
                "survey programming",
                "technical marketing",
                "technology",
                "technology solutions",
                "user acquisition",
                "user growth",
                "value proposition",
                "value-oriented content development",
                "web analytics",
                "web design",
                "web development",
                "webinar development"
            ]
        },
        "Customer Insights and Analytics": {
            "soft skills": [
                "ability",
                "accountability",
                "accurate",
                "adaptability",
                "adaptable",
                "analytical",
                "analytical mindset",
                "analytical skills",
                "attention to detail",
                "attention to details",
                "automation",
                "collaboration",
                "communication",
                "creative thinking",
                "creativity",
                "critical thinking",
                "critical-thinking",
                "curiosity",
                "decision-making",
                "detail-oriented",
                "exposition",
                "flexibility",
                "flexible",
                "goal-oriented",
                "influencing",
                "innovation",
                "interact",
                "interpersonal",
                "interpersonal skills",
                "leadership",
                "listening",
                "mentoring",
                "organization",
                "passion",
                "passionate",
                "people skills",
                "persistence",
                "proactive",
                "proactivity",
                "problem solving",
                "problem-solving",
                "research",
                "results-driven",
                "self-motivated",
                "self-motivation",
                "stress-resistant",
                "teamwork",
                "time management",
                "troubleshooting",
                "trust",
                "versatile",
                "work effectively"
            ],
            "technical skills": [
                ".Net environment",
                "A/B experimentation",
                "A/B experiments",
                "A/B testing",
                "AI-driven services",
                "AI/ML Model development",
                "AI/ML algorithms",
                "API",
                "API Management",
                "API development",
                "API integration",
                "API integrations",
                "API management",
                "API services",
                "APIs",
                "AWS",
                "AWS cloud services",
                "AWS data pipelines",
                "AWS services",
                "Agile methodologies",
                "Airflow",
                "Angular",
                "Apache Airflow",
                "Apache Druid",
                "Apache Kafka",
                "Apache Spark",
                "Argo",
                "Azure",
                "Azure Data Factory",
                "Azure DevOps",
                "Azure Functions",
                "Azure security practices",
                "BI",
                "BI Tools",
                "BI solutions",
                "BI tools",
                "BI/software development",
                "Big Data platforms",
                "BigQuery",
                "Bokeh",
                "C#",
                "C++",
                "CI/CD",
                "CI/CD pipelines",
                "CI/CD practices",
                "Celery",
                "Clickhouse",
                "Confluent Kafka",
                "Cron jobs",
                "Cube OLAP",
                "DBT",
                "Data Warehouse design",
                "DataFrames",
                "Databrick",
                "Datadog",
                "Deep Learning",
                "DevOps",
                "Django",
                "Docker",
                "EC2",
                "ETL",
                "ETL frameworks",
                "ETL libraries",
                "ETL modeling",
                "ETL processes",
                "ETL technologies",
                "ETL/ELT",
                "ETL/ELT pipelines",
                "ETL/ELT processes",
                "ETL/ELT workflow",
                "ElasticSearch",
                "Excel",
                "Flask",
                "Fortran",
                "GCP",
                "Git",
                "GitHub Actions",
                "Github",
                "Gitlab",
                "Google Cloud",
                "Google Cloud Platform",
                "HTML",
                "HTTP/HTTPS",
                "Hadoop",
                "Hive",
                "Hortonworks",
                "IAM",
                "Impala",
                "JSON",
                "Java",
                "JavaScript",
                "Jenkins",
                "Jenkins Pipeline",
                "Jira",
                "Julia",
                "Kafka",
                "Kubernetes",
                "Linux",
                "Logic Apps",
                "Looker",
                "ML",
                "MLOps",
                "MLOps practices",
                "MLlib",
                "MS SQL",
                "MS SQL Server",
                "MS SQL database",
                "Machine Learning",
                "Map Reduce",
                "MapReduce",
                "Matlab",
                "Matplotlib",
                "Microsoft Azure",
                "Microsoft Excel",
                "MongoDB",
                "NLP",
                "NLP algorithms",
                "NLP models",
                "NN",
                "No-SQL",
                "NoSQL",
                "NoSQL databases",
                "Notebooks",
                "Numpy",
                "OAuth",
                "Optimization",
                "PROD",
                "Pandas",
                "PgSQL",
                "Polars",
                "Postgres",
                "Power BI",
                "PowerBI",
                "Predictive Modeling",
                "Presto",
                "PySpark",
                "PyTorch",
                "Pyspark",
                "Pytest",
                "Python",
                "Python programming",
                "Python scripting",
                "QA",
                "R",
                "R/Python",
                "REST",
                "REST APIs",
                "RESTful API",
                "RabbitMQ",
                "React",
                "RedShift",
                "Redis",
                "Redshift",
                "S3",
                "SAS",
                "SDLC practices",
                "SQL",
                "SQL Alchemy",
                "SQL Relational databases",
                "SQL coding",
                "SQL optimization",
                "SQL queries",
                "Scala",
                "Scikit Learn",
                "Scikit-learn",
                "ScyllaDB",
                "Sentry",
                "Snowflake",
                "Spark",
                "Spark Streaming",
                "Spark/Databricks",
                "SparkML",
                "Splunk",
                "Tableau",
                "Tabular",
                "TensorFlow",
                "Tensorflow",
                "Terraform",
                "WebServices",
                "Windows",
                "Windows environments",
                "Zeppelin",
                "advanced data science",
                "agile development",
                "agile methodologies",
                "agile software development",
                "agile/scrum methodology",
                "algebra",
                "algorithms",
                "algorithms development",
                "analysis",
                "analytical skills",
                "analytics",
                "analytics engineering",
                "analytics techniques",
                "apis",
                "architecture patterns",
                "automated integration tests",
                "automation",
                "automation processes",
                "automation techniques",
                "automation tools",
                "big data",
                "big data platforms",
                "big data technologies",
                "big data tools",
                "bug fixing",
                "build",
                "build strategies",
                "business intelligence",
                "c++",
                "campaign experimentation",
                "change control",
                "ci/cd",
                "cloud architecture",
                "cloud computing",
                "cloud environment deployment",
                "cloud experience",
                "cloud migration",
                "cloud native",
                "cloud platforms",
                "cloud services",
                "cloud technologies",
                "cloud-based platforms",
                "cloud-based solutions",
                "code release",
                "code review",
                "code reviews",
                "code writing",
                "coding",
                "collaboration",
                "communication",
                "compliance",
                "computational complexity theory",
                "computer vision",
                "configuration",
                "containerisation technology",
                "containerization",
                "content conversion",
                "content modeling",
                "content use",
                "continuous integration",
                "ctDNA analysis",
                "customer analytics",
                "dashboard development",
                "dashboard systems",
                "dashboards",
                "data",
                "data APIs",
                "data QC",
                "data aggregation",
                "data analysis",
                "data analysis documentation",
                "data analysis techniques",
                "data analytics",
                "data architecture",
                "data cleaning",
                "data cleansing",
                "data conversion",
                "data curation",
                "data documentation",
                "data engineering",
                "data engineering understanding",
                "data enhancement",
                "data extraction",
                "data flow",
                "data flow modeling",
                "data governance",
                "data hygiene",
                "data informatics",
                "data infrastructure",
                "data ingestion",
                "data insights",
                "data integration",
                "data integrations",
                "data integrity",
                "data integrity checks",
                "data interpretation",
                "data lakes",
                "data lineage",
                "data load modeling",
                "data management",
                "data management solutions",
                "data manipulation",
                "data mapping",
                "data mining",
                "data modeling",
                "data modelling",
                "data pipeline",
                "data pipeline architecture",
                "data pipeline orchestration",
                "data pipelines",
                "data platform development",
                "data post-processing",
                "data pre-processing",
                "data preprocessing",
                "data privacy",
                "data processing",
                "data profiling",
                "data projects",
                "data quality",
                "data quality assessment",
                "data quality checks",
                "data quality framework",
                "data querying",
                "data reporting",
                "data repositories",
                "data science",
                "data science methodologies",
                "data science packages proficiency",
                "data science process",
                "data science programming",
                "data science projects",
                "data science software languages",
                "data science techniques",
                "data science visualization",
                "data security",
                "data storage",
                "data streaming",
                "data streaming architectures",
                "data structures",
                "data structuring",
                "data systems",
                "data technology",
                "data testing",
                "data transformation",
                "data validation",
                "data virtualization",
                "data visualization",
                "data visualization tools",
                "data warehouse",
                "data warehouse management",
                "data warehouse modeling",
                "data warehouses",
                "data warehousing",
                "data wrangling",
                "data-related tasks",
                "database",
                "database administration",
                "database architecture",
                "database backup",
                "database concepts",
                "database design",
                "database implementation",
                "database knowledge",
                "database management",
                "database performance tuning",
                "database programming",
                "database query analysis",
                "database query analysis/optimization",
                "database systems",
                "databases",
                "dbt",
                "deep learning",
                "deep learning algorithms",
                "design",
                "development collaboration tools",
                "dimensional modeling",
                "distributed computing",
                "distributed computing systems",
                "distributed model training",
                "distributed systems",
                "editing tools",
                "ensemble modeling",
                "enterprise frameworks",
                "enterprise reporting",
                "etl",
                "etl processes",
                "event orchestration tools",
                "event streaming",
                "event-driven architecture",
                "experiment design",
                "experimental design",
                "experimentation",
                "feature engineering",
                "financial modeling",
                "financial planning",
                "fine-tuning LLMs",
                "forecasting",
                "functional programming",
                "git",
                "graph algorithms",
                "graphing and dashboard systems",
                "graphing systems",
                "hadoop",
                "information retrieval",
                "information security",
                "information technology",
                "infrastructure architecture",
                "integrating data sources",
                "integration",
                "integration platforms",
                "integration tests",
                "integrity checks",
                "java",
                "logical data models",
                "machine learning",
                "machine learning algorithms",
                "machine learning models",
                "machine learning techniques",
                "machine-learning",
                "machine-learning algorithms",
                "machine-learning models",
                "management",
                "material discovery",
                "material informatics",
                "material sustainability",
                "math",
                "mathematical foundations",
                "mathematical optimization",
                "mathematics",
                "message queuing",
                "metadata",
                "metadata cataloging",
                "metadata generation",
                "metadata management",
                "metadata usage",
                "microservice",
                "model deployment",
                "model development",
                "model evaluation",
                "model performance improvement",
                "model training",
                "modeling",
                "monitoring and logging frameworks",
                "monitoring processes",
                "multi-omics biomarker discovery",
                "natural language processing",
                "neoantigen prediction",
                "neural networks",
                "object-oriented",
                "object-oriented programming",
                "object-oriented scripting",
                "ontologies",
                "optimization",
                "optimization algorithms",
                "optimization techniques",
                "orchestration/workflow management",
                "outlier detection",
                "pathways analysis",
                "physical data models",
                "predictive modeling",
                "predictive models",
                "probability",
                "problem resolution",
                "problem-solving",
                "process improvement",
                "production-ready code writing",
                "programming",
                "programming languages",
                "prototyping",
                "public cloud platforms",
                "python",
                "python proficiency",
                "python programming",
                "pytorch",
                "qualitative",
                "qualitative analysis",
                "quantitative",
                "quantitative analysis",
                "query language",
                "query languages",
                "real-time data processing",
                "real-time processing frameworks",
                "realtime streaming",
                "recovery procedures",
                "relational databases",
                "relational modeling",
                "release management",
                "reporting packages",
                "requirements analysis",
                "root cause analysis",
                "salesforce administration",
                "scala",
                "scalable",
                "scripting",
                "security",
                "segmentation",
                "sklearn",
                "software design",
                "software development",
                "software development lifecycle",
                "software engineering",
                "spark",
                "sql",
                "statistical analysis",
                "statistical modeling",
                "statistical programming",
                "statistical software",
                "statistical techniques",
                "statistical tools",
                "statistics",
                "strategic thinking",
                "strategy development",
                "stream processing",
                "stream-processing systems",
                "system development",
                "test automation",
                "testing",
                "testing strategies",
                "text mining",
                "tools implementation",
                "transformation",
                "transformation activities",
                "unit testing",
                "version control",
                "version control systems",
                "visualisation",
                "visualization",
                "web app architecture understanding",
                "web-based applications",
                "workflow",
                "workflow management"
            ]
        },
        "Market Research": {
            "soft skills": [
                "accountability",
                "adaptability",
                "analytical",
                "analytical skills",
                "business acumen",
                "collaboration",
                "communication",
                "continuous improvement",
                "creative thinking",
                "creativity",
                "critical thinking",
                "detail oriented",
                "drive",
                "eagerness to learn",
                "efficiency",
                "emotional intelligence",
                "engagement",
                "flexibility",
                "flexible mindset",
                "follow through",
                "independence",
                "influencing",
                "initiative",
                "innovation",
                "inquiry",
                "integrity",
                "interpersonal",
                "interpersonal skills",
                "leadership",
                "organization",
                "ownership",
                "positive working relationships",
                "presentation",
                "prioritization",
                "proactivity",
                "problem solving",
                "problem-solving",
                "relationship-building",
                "research",
                "results-driven",
                "self-assessment",
                "self-awareness",
                "self-starter",
                "solution-oriented",
                "supporting",
                "teamwork",
                "time management",
                "trust"
            ],
            "technical skills": [
                "ADO",
                "API integration",
                "AS400",
                "AWS",
                "AWS (EC2, S3, RDS, Redshift, EMR)",
                "Alteryx",
                "Athena",
                "Atomic Scope",
                "Azure AI/ML platform",
                "BI",
                "BI Tools",
                "BigQuery",
                "BizTalk360",
                "C",
                "C#",
                "C++",
                "CI/CD",
                "Confluence",
                "Data Analysis",
                "Data warehousing",
                "Django",
                "Document360",
                "ETL",
                "ETL data processing",
                "ETL frameworks",
                "ETL processes",
                "Excel",
                "Fast API",
                "Flask",
                "Fortran",
                "Gitlab",
                "Google Analytics",
                "Google Tag Manager",
                "Graph Sigma",
                "Grooper",
                "HTML/CSS",
                "Hadoop",
                "Hive",
                "JIRA",
                "Java",
                "JavaScript",
                "Jira",
                "Julia",
                "Looker",
                "MS SQL",
                "Microsoft Excel",
                "Microsoft Office 365 Suite",
                "MySQL",
                "No-SQL",
                "Power BI",
                "Power Pivot",
                "Power Query",
                "PowerPoint",
                "PyTorch",
                "Python",
                "Python programming",
                "QlikSense",
                "Qualtrics",
                "QuickSight",
                "R",
                "React",
                "RedShift",
                "Redshift",
                "Relational Databases",
                "SAS",
                "SAS Macros",
                "SEO",
                "SPSS",
                "SQL",
                "SQL Alchemy",
                "SQL coding",
                "SQL optimization",
                "SSRS",
                "Scala",
                "Serverless360",
                "SparkML",
                "Spotfire",
                "Tableau",
                "Tensorflow",
                "UAT testing",
                "UiPath",
                "VBA",
                "Visual Studio",
                "XML",
                "agile methodologies",
                "algorithm design",
                "algorithm development",
                "algorithms",
                "analytical skills",
                "analytics",
                "analytics engineering",
                "automation",
                "aws",
                "big data analytics",
                "business acumen",
                "business analysis",
                "business intelligence",
                "business planning",
                "business process analysis",
                "c++",
                "cloud environment",
                "cloud environment deployment",
                "cloud technologies",
                "coding",
                "compilers",
                "complex algorithms",
                "computational complexity theory",
                "computational modelling",
                "containerisation technology",
                "course content",
                "dashboard design",
                "dashboard development",
                "dashboards",
                "data analysis",
                "data analytics",
                "data capacity",
                "data cleaning",
                "data cleansing",
                "data collection",
                "data entry",
                "data extraction",
                "data gathering",
                "data governance",
                "data ingestion",
                "data integration",
                "data interpretation",
                "data literacy",
                "data management",
                "data metrics",
                "data mining",
                "data modeling",
                "data models",
                "data preparation",
                "data preprocessing",
                "data processing",
                "data quality",
                "data quality analysis",
                "data quality management",
                "data quality rules",
                "data science",
                "data strategies",
                "data structuring",
                "data visualisation",
                "data visualization",
                "data visualization libraries",
                "database applications",
                "database design",
                "database knowledge",
                "database management",
                "database query analysis",
                "database query optimization",
                "database review",
                "database skills",
                "debugging",
                "deep learning",
                "development collaboration tools",
                "distributed model training",
                "excel",
                "experimental design",
                "experimentation",
                "experimentation design",
                "exploratory data analysis",
                "feature engineering",
                "financial analysis",
                "fortran",
                "geometry",
                "ggplot",
                "git",
                "graph mining",
                "information extraction",
                "information retrieval",
                "internet research",
                "javascript",
                "jenkins",
                "jira",
                "knowledge management",
                "machine learning",
                "machine-learning",
                "machine-learning algorithms",
                "market research",
                "market research analysis",
                "market research methodologies",
                "material informatics",
                "math",
                "mathematical foundations",
                "mathematics",
                "model evaluation",
                "model training",
                "natural language processing",
                "network programming",
                "numerical analysis",
                "operating systems",
                "optimization algorithms",
                "pandas",
                "phone etiquette",
                "predictive modeling",
                "predictors",
                "product analytics",
                "programming",
                "prototyping",
                "pytest",
                "python",
                "python programming",
                "pytorch",
                "qualitative research techniques",
                "quantitative analysis",
                "quantitative research",
                "query language",
                "r",
                "reporting",
                "reporting processes",
                "research",
                "root cause analysis",
                "scientific principles",
                "scikit-learn",
                "screening",
                "segmentation techniques",
                "sklearn",
                "software development",
                "software development life cycle",
                "sql",
                "state of the art technology",
                "statistical analysis",
                "statistical modeling",
                "statistical tools",
                "statistics",
                "survey research",
                "technology solutions",
                "tensorflow",
                "troubleshooting",
                "visualization",
                "web mining"
            ]
        },
        "Creative Services": {
            "soft skills": [
                "accessibility",
                "accountability",
                "achievable",
                "across",
                "active",
                "adaptability",
                "agility",
                "alignment",
                "allocation",
                "ambiguity",
                "analytical",
                "attention",
                "attention to detail",
                "audience",
                "audio",
                "automation",
                "automations",
                "autonomy",
                "available",
                "awareness",
                "blending",
                "brand",
                "brand management",
                "building",
                "collaboration",
                "collaborative",
                "communication",
                "complex",
                "concurrent",
                "consistent",
                "content",
                "copy",
                "creating",
                "creative",
                "creative thinking",
                "creativity",
                "critical thinking",
                "curiosity",
                "curious",
                "customer service",
                "customer-centric",
                "data-driven",
                "defined",
                "delivering",
                "design",
                "detail",
                "determining",
                "develop",
                "develops",
                "digital",
                "direction",
                "document",
                "drive",
                "dynamic",
                "effective",
                "empathy",
                "engagement",
                "enthusiasm",
                "environments",
                "executing",
                "fast-paced",
                "findings",
                "flexibility",
                "formulate",
                "framework",
                "graphic",
                "growth",
                "guidance",
                "health",
                "impactful",
                "improvements",
                "in-depth",
                "incorporates",
                "increasing",
                "industry",
                "initiative",
                "innovation",
                "interaction",
                "interpersonal",
                "interpersonal skills",
                "intuition",
                "investment",
                "journeys",
                "key",
                "leadership",
                "leading",
                "maintain",
                "market",
                "media",
                "mediums",
                "meeting management",
                "mentoring",
                "mindset",
                "mix",
                "model",
                "monitor",
                "motivation",
                "multiple",
                "navigating",
                "negotiation",
                "objectives",
                "openness",
                "operation",
                "operational",
                "optimal",
                "optimization",
                "organization",
                "organizational",
                "organizational skills",
                "organize",
                "overview",
                "ownership",
                "pace",
                "passion",
                "passionate",
                "personal accountability",
                "personalization",
                "personalized",
                "photography",
                "planning",
                "presence",
                "presentation",
                "principles",
                "priorities",
                "prioritization",
                "prioritize",
                "proactiveness",
                "problem solving",
                "problem-solving",
                "producing",
                "productivity",
                "professionalism",
                "programs",
                "progress",
                "project management",
                "projects",
                "provide",
                "quantitative",
                "range",
                "reinforcing",
                "relationship management",
                "relationship-building",
                "relevant",
                "reporting",
                "research",
                "resilience",
                "rigour",
                "scheduling",
                "segments",
                "self-starter",
                "self-sufficiency",
                "services",
                "setting",
                "solution-oriented",
                "spanning",
                "standard",
                "standardization",
                "standards",
                "static",
                "strategic",
                "strategic mindset",
                "strategic thinking",
                "strategy",
                "strong",
                "tailored",
                "target",
                "teamwork",
                "thoughtfulness",
                "time management",
                "time-management",
                "timelines",
                "tracking",
                "trends",
                "triggers",
                "understanding",
                "using",
                "valuable",
                "vendor relations",
                "video",
                "workload",
                "writing"
            ],
            "technical skills": [
                "3D",
                "3D animation",
                "AAA games development",
                "AR graphics",
                "Adobe",
                "Adobe Acrobat",
                "Adobe CC",
                "Adobe Creative Suite",
                "Adobe Illustrator",
                "Adobe InDesign",
                "Adobe Photoshop",
                "Adobe Suite",
                "Ads",
                "After",
                "After Effects",
                "Analytics",
                "Animate",
                "Arabic",
                "Asana",
                "Audition",
                "A|B testing",
                "B2B marketing",
                "B2C industries",
                "CMS",
                "CRM",
                "CRM database maintenance",
                "CRM management",
                "CRM systems",
                "CSS",
                "Campaign",
                "Canva",
                "Confluence",
                "Content Management Systems",
                "Content Strategy",
                "Cut",
                "Display Advertising",
                "Dreamweaver",
                "Eastern",
                "Effects",
                "English",
                "ExactTarget",
                "Excel",
                "FTP",
                "Facebook",
                "Figma",
                "FinTech",
                "Final",
                "Final Cut Pro",
                "Flash",
                "GTM strategy",
                "Google",
                "Google Ads",
                "Google Analytics",
                "Google Looker Studio",
                "Google Slides",
                "Google Suite",
                "HTML",
                "HTML/CSS",
                "IT",
                "Illustrator",
                "Instagram",
                "JIRA",
                "Keynote",
                "LinkedIn",
                "LinkedIn Ads",
                "MS Office",
                "MS365",
                "Media Planning",
                "Meta Ads",
                "Microsoft",
                "Microsoft PowerPoint",
                "Middle",
                "P&L management",
                "PDF",
                "Perforce",
                "Photoshop",
                "PowerPoint",
                "Premiere",
                "Premiere Pro",
                "Pro",
                "QA",
                "Responsys",
                "SEM",
                "SEO",
                "SEO keyword research",
                "SEO knowledge",
                "SEO optimization",
                "SEO techniques",
                "SEO tools",
                "SEO writing",
                "SQL",
                "SaaS/Cloud leasing/loan knowledge",
                "Salesforce",
                "TikTok Ads",
                "Twitter",
                "UI",
                "UI design",
                "UI/UX",
                "UI/UX design",
                "UX",
                "UX design",
                "UX/UI",
                "UX/UI design",
                "WordPress",
                "Wordpress",
                "YouTube",
                "account/project management",
                "adobe creative suite",
                "advertisements",
                "advertising",
                "advertising campaigns",
                "advertising fundamentals",
                "agile methodologies",
                "analytical",
                "analytics",
                "animation",
                "animation planning",
                "animations",
                "apparel production",
                "applications",
                "architecture",
                "art design",
                "art direction",
                "artwork",
                "asset management",
                "attribution reporting",
                "audio engineering",
                "audio setup",
                "augmented reality",
                "automation",
                "blog writing",
                "blogging",
                "brand",
                "brand awareness",
                "brand communication",
                "brand design",
                "brand development",
                "brand guidelines",
                "brand health checks",
                "brand identities",
                "brand identity",
                "brand integrity management",
                "brand management",
                "brand renovation",
                "brand strategy",
                "branding",
                "budget management",
                "business administration",
                "business analysis",
                "business strategies",
                "camera operation",
                "campaign development",
                "campaign evaluation",
                "campaign execution",
                "campaign management",
                "campaign optimization",
                "campaigns",
                "color correction",
                "color theory",
                "colors",
                "colour theory",
                "communication",
                "compatibility",
                "competitive analysis",
                "competitive intelligence",
                "compositing",
                "composition",
                "composition techniques",
                "consumer tech",
                "content",
                "content creation",
                "content development",
                "content marketing",
                "content optimization",
                "content production",
                "content research",
                "content strategies",
                "content strategy",
                "content writing",
                "copywriting",
                "creating compelling scenes",
                "creative",
                "creative briefs",
                "creative concept arts",
                "creative concept development",
                "creative concepts",
                "creative design",
                "creative strategy",
                "cross-browser",
                "customer experience data",
                "data analysis",
                "data analytics",
                "data validation",
                "data visualization",
                "database management",
                "demand generation",
                "design",
                "design principles",
                "design review",
                "design tools",
                "designs",
                "development",
                "development scheduling",
                "digital advertising",
                "digital analytics",
                "digital artwork",
                "digital asset management",
                "digital design",
                "digital display campaigns",
                "digital marketing",
                "digital marketing metrics",
                "digital media",
                "digital technology",
                "direction",
                "editing",
                "editing software",
                "editing software packages",
                "effects",
                "elements",
                "email",
                "email campaign management",
                "email design",
                "email marketing",
                "email marketing design",
                "email/push distribution",
                "engine systems",
                "enhancement",
                "event evaluation",
                "event logistics",
                "event management",
                "event planning",
                "event promotions",
                "excel operation",
                "experience",
                "fashion design",
                "filmmaking",
                "fonts",
                "footage",
                "full funnel content strategy",
                "game capture editing",
                "game development",
                "game engine",
                "game ideation",
                "generative AI",
                "generative development",
                "go-to-market planning",
                "go-to-market strategy",
                "google analytics",
                "graphic",
                "graphic design",
                "graphics design",
                "growth marketing",
                "guidelines",
                "hardware troubleshooting",
                "hosting",
                "html",
                "icon design",
                "ideation",
                "illustration",
                "illustrations",
                "illustrator",
                "image editing",
                "image manipulation",
                "image preparation",
                "images",
                "imported products management",
                "infographic design",
                "infographics",
                "information architecture",
                "interaction design",
                "interactive",
                "interactive apps",
                "interfaces",
                "internal communication",
                "internet",
                "issues",
                "iteration",
                "journalism",
                "keyword research",
                "layout composition",
                "layout design",
                "layout principles",
                "layouts",
                "lead generation",
                "level design",
                "license guidelines",
                "light and sound design",
                "light design",
                "lighting",
                "local seo",
                "localization",
                "logos",
                "maintenance",
                "management",
                "manipulating",
                "market",
                "market analysis",
                "market expansion",
                "market insight",
                "market performance analysis",
                "market research",
                "market research analysis",
                "market visits",
                "market-oriented content",
                "marketing",
                "marketing analytics",
                "marketing automation",
                "marketing campaigns",
                "marketing trends analysis",
                "materials",
                "mechanical engineering",
                "media",
                "media activity",
                "media buying models",
                "media management",
                "merchandising",
                "messaging",
                "mobile",
                "mobile design",
                "motion capture feedback",
                "motion graphic skills",
                "motion graphics",
                "multimedia",
                "multimedia design",
                "next gen game development",
                "on-screen overlays",
                "optimization",
                "organic search",
                "organic search rankings",
                "organic social media strategies",
                "organizational skills",
                "pacing",
                "paid search",
                "paid social media advertising",
                "performance marketing",
                "photo editing",
                "photography",
                "platforms",
                "positioning",
                "post-processing",
                "post-production",
                "ppc campaigns",
                "presentation design",
                "print",
                "print design",
                "print production",
                "problem solving",
                "product design",
                "product development",
                "product innovation",
                "product launch",
                "product launch execution",
                "product launch management",
                "product launch planning",
                "product launches",
                "product management",
                "product marketing",
                "product positioning",
                "product surveys",
                "product-thinking",
                "project management",
                "project tracking methodologies",
                "projects",
                "proofreading",
                "prototypes",
                "prototyping",
                "public relations",
                "qualitative analysis",
                "quality",
                "quantitative",
                "quantitative analysis",
                "quantitative methods",
                "regulatory",
                "relationship management",
                "rendering",
                "reporting",
                "research",
                "responsive",
                "retouching",
                "sales",
                "sales enablement",
                "sales presentation",
                "sales tool development",
                "scripting",
                "search engine optimization",
                "sem campaigns",
                "seo",
                "setup",
                "social",
                "social media",
                "social media design",
                "social media management",
                "social media marketing",
                "social media strategy",
                "social media trends",
                "software",
                "software development",
                "software products",
                "software troubleshooting",
                "sound design",
                "spatial design",
                "special effects",
                "staging",
                "storyboarding",
                "storyboards",
                "storytelling",
                "strategy",
                "streaming",
                "targeting efficiency",
                "technical art",
                "technical production",
                "techniques",
                "technology",
                "template localization",
                "testing",
                "time management",
                "transitions",
                "troubleshooting",
                "typography",
                "unreal engine",
                "user",
                "user acquisition",
                "user engagement",
                "user experience",
                "user experience design",
                "user growth",
                "user research",
                "vendor negotiation",
                "venue selection",
                "video",
                "video animation",
                "video editing",
                "video production",
                "video walls",
                "videography",
                "virtual sets",
                "visual",
                "visual communication",
                "visual design",
                "visual storytelling",
                "visual styles",
                "waterfall methodologies",
                "web",
                "web SaaS platforms",
                "web application design",
                "web design",
                "web development",
                "web traffic analysis",
                "webinar execution",
                "webinar scheduling",
                "webinars",
                "website content maintenance",
                "website optimization",
                "website updates",
                "websites",
                "wireframing",
                "workflow software",
                "writing"
            ]
        },
        "Events and Experiences": {
            "soft skills": [
                "analytical",
                "collaboration",
                "communication",
                "flexibility",
                "interpersonal",
                "leadership",
                "negotiation",
                "organization",
                "teamwork"
            ],
            "technical skills": [
                "budgeting",
                "business",
                "communication",
                "data analysis",
                "event coordination",
                "event management",
                "event planning",
                "logistics",
                "management",
                "marketing",
                "negotiation",
                "operations",
                "procurement",
                "programming",
                "project management",
                "researching",
                "sourcing",
                "usability testing",
                "user research"
            ]
        },
        "Public Relations": {
            "soft skills": [
                "collaboration",
                "communication",
                "creativity",
                "empathy",
                "empowerment",
                "inspiration",
                "interpersonal",
                "leadership",
                "networking",
                "organization",
                "problem-solving",
                "public speaking",
                "relationship building",
                "teamwork",
                "time management"
            ],
            "technical skills": [
                "Excel",
                "Forms",
                "Microsoft Office Suite",
                "SEO",
                "Teams",
                "Word",
                "audio production",
                "bilingual",
                "cold call",
                "communication strategy",
                "content creation",
                "copywriting",
                "customer service",
                "data recording",
                "digital marketing",
                "digital publishing",
                "editing",
                "event management",
                "fact-checking",
                "graphic design",
                "journalism",
                "marketing",
                "media relations",
                "photography",
                "project management",
                "public relations",
                "sales",
                "social media",
                "social media content creation",
                "strategic thinking",
                "time-management",
                "video production",
                "web traffic analysis"
            ]
        }
    }
}